nats_queue/__init__.py
nats_queue/nats_job.py
nats_queue/nats_limiter.py
nats_queue/nats_queue.py
nats_queue/nats_worker.py
nats_queue-1.1.5.dist-info/LICENSE
nats_queue-1.1.5.dist-info/METADATA
nats_queue-1.1.5.dist-info/WHEEL
nats_queue-1.1.5.dist-info/RECORD
